setup.py
dist_alx/Binomial.py
dist_alx/Distribution.py
dist_alx/Gaussian.py
dist_alx/__init__.py
dist_alx_codeasyb.egg-info/PKG-INFO
dist_alx_codeasyb.egg-info/SOURCES.txt
dist_alx_codeasyb.egg-info/dependency_links.txt
dist_alx_codeasyb.egg-info/not-zip-safe
dist_alx_codeasyb.egg-info/top_level.txt