Metadata-Version: 2.1
Name: dist-alx-codeasyb
Version: 0.0
Summary: Gaussian and Binomial distributions
Home-page: UNKNOWN
Author-email: techamir25@gmail.com
License: UNKNOWN
Platform: UNKNOWN
